kombini/__init__.py
kombini/android_check.py
kombini/duration_str.py
kombini/ffprobe_info.py
kombini/home_tilde.py
kombini/item_counter.py
kombini/json_util.py
kombini/parallel.py
kombini/py.typed
kombini/recurse_paths.py
kombini/remove_diacritic.py
kombini/retrieve_url.py
kombini/safe_filename.py
kombini-0.0.3.dist-info/METADATA
kombini-0.0.3.dist-info/WHEEL
kombini-0.0.3.dist-info/top_level.txt
kombini-0.0.3.dist-info/zip-safe
kombini-0.0.3.dist-info/RECORD
